cacheout/__init__.py
cacheout/cache.py
cacheout/fifo.py
cacheout/lfu.py
cacheout/lifo.py
cacheout/lru.py
cacheout/manager.py
cacheout/memoization.py
cacheout/mru.py
cacheout/rr.py
cacheout/stats.py
cacheout-0.16.0.dist-info/AUTHORS.rst
cacheout-0.16.0.dist-info/LICENSE.rst
cacheout-0.16.0.dist-info/METADATA
cacheout-0.16.0.dist-info/WHEEL
cacheout-0.16.0.dist-info/top_level.txt
cacheout-0.16.0.dist-info/RECORD
